architect/sdk/__init__.py
architect.sdk-0.2.1.dist-info/LICENSE.txt
architect.sdk-0.2.1.dist-info/METADATA
architect.sdk-0.2.1.dist-info/WHEEL
architect.sdk-0.2.1.dist-info/top_level.txt
architect.sdk-0.2.1.dist-info/RECORD
