Metadata-Version: 2.1
Name: architect.sdk
Version: 0.2.1
Summary: Architect Python SDK
Home-page: https://github.com/architect-team/python-sdk
Author: architect.io
Author-email: packages@architect.io
License: GPL-3.0
Platform: UNKNOWN
